aspreno/__init__.py
aspreno/_utils.py
aspreno/global_handler.py
aspreno/py.typed
LICENSE
aspreno-1.0.0.dev2.dist-info/LICENSE
aspreno-1.0.0.dev2.dist-info/WHEEL
aspreno-1.0.0.dev2.dist-info/METADATA
aspreno-1.0.0.dev2.dist-info/RECORD
